prefab_cloud_python/__init__.py
prefab_cloud_python/_internal_constants.py
prefab_cloud_python/_internal_setup.py
prefab_cloud_python/_processors.py
prefab_cloud_python/client.py
prefab_cloud_python/config_client.py
prefab_cloud_python/config_loader.py
prefab_cloud_python/config_parser.py
prefab_cloud_python/config_resolver.py
prefab_cloud_python/config_value_unwrapper.py
prefab_cloud_python/config_value_wrapper.py
prefab_cloud_python/constants.py
prefab_cloud_python/context.py
prefab_cloud_python/context_shape.py
prefab_cloud_python/context_shape_aggregator.py
prefab_cloud_python/criteria_evaluator.py
prefab_cloud_python/encryption.py
prefab_cloud_python/feature_flag_client.py
prefab_cloud_python/log_path_aggregator.py
prefab_cloud_python/logger_client.py
prefab_cloud_python/multi_processor.py
prefab_cloud_python/options.py
prefab_cloud_python/read_write_lock.py
prefab_cloud_python/weighted_value_resolver.py
prefab_cloud_python/yaml_parser.py
prefab_pb2.py
prefab_pb2_grpc.py
prefab_cloud_python_testing-0.9.1.dev0.dist-info/LICENSE.txt
prefab_cloud_python_testing-0.9.1.dev0.dist-info/METADATA
prefab_cloud_python_testing-0.9.1.dev0.dist-info/WHEEL
prefab_cloud_python_testing-0.9.1.dev0.dist-info/RECORD
