Metadata-Version: 2.1
Name: prefab-cloud-python-testing
Version: 0.9.1.dev0
Summary: Python client for Prefab Feature Flags, Dynamic log levels, and Config as a Service: https://www.prefab.cloud
Home-page: https://www.prefab.cloud
License: MIT
Author: Michael Berkowitz
Author-email: michael.berkowitz@gmail.com
Maintainer: Michael Berkowitz
Maintainer-email: michael.berkowitz@gmail.com
Requires-Python: >=3.9,<4
Classifier: License :: OSI Approved :: MIT License
Classifier: Programming Language :: Python :: 3
Classifier: Programming Language :: Python :: 3.9
Classifier: Programming Language :: Python :: 3.10
Classifier: Programming Language :: Python :: 3.11
Classifier: Programming Language :: Python :: 3.12
Requires-Dist: cryptography (>=41.0.7)
Requires-Dist: grpcio (>=1.48.4)
Requires-Dist: mmh3 (>=3.0.0,<4.0.0)
Requires-Dist: pyyaml (>=6.0.0,<7.0.0)
Requires-Dist: requests (>=2.28.0,<3.0.0)
Requires-Dist: sseclient-py (>=1.7.2,<2.0.0)
Requires-Dist: structlog (>=22.3,<23.0)
Project-URL: Documentation, https://docs.prefab.cloud/docs/python-sdk/python
Project-URL: Repository, https://github.com/prefab-cloud/prefab-cloud-python
